nade/__init__.py
nade/data/__init__.py
nade/data/socialmedia_en/emoji_frequencies.jsonl
nade/data/socialmedia_en/nade_250k_hp.ftz
nade/data/socialmedia_en/reg_anger.txt.gz
nade/data/socialmedia_en/reg_anticipation.txt.gz
nade/data/socialmedia_en/reg_disgust.txt.gz
nade/data/socialmedia_en/reg_fear.txt.gz
nade/data/socialmedia_en/reg_joy.txt.gz
nade/data/socialmedia_en/reg_sadness.txt.gz
nade/data/socialmedia_en/reg_surprise.txt.gz
nade/data/socialmedia_en/reg_trust.txt.gz
nade/nade.py
nade-0.3.1.dist-info/LICENSE
nade-0.3.1.dist-info/METADATA
nade-0.3.1.dist-info/WHEEL
nade-0.3.1.dist-info/RECORD
