Metadata-Version: 2.3
Name: nade
Version: 0.3.1
Summary: Natural affect detection allows to infer basic emotions from social media messages
License: MIT
Author: Christian Hotz-Behofsits
Requires-Python: >=3.9
Classifier: License :: OSI Approved :: MIT License
Classifier: Programming Language :: Python :: 3
Classifier: Programming Language :: Python :: 3.9
Classifier: Programming Language :: Python :: 3.10
Classifier: Programming Language :: Python :: 3.11
Classifier: Programming Language :: Python :: 3.12
Classifier: Programming Language :: Python :: 3.13
Requires-Dist: fasttext-numpy2 (>=0.10.4)
Requires-Dist: lightgbm (>=3.2)
Requires-Dist: numpy (>=2.0.0)
Requires-Dist: pyarrow (>=15.0.0)
Requires-Dist: pybind11 (>=2.0)
Project-URL: Bug Tracker, https://github.com/inkrement/nade/issues
Project-URL: Homepage, https://nade-explorer.inkrement.ai/
Project-URL: Repository, https://github.com/inkrement/nade.git
